{"info": {"show number": 6744, "date": "2014-01-02", "game_id": 4386, "game_comments": "Jerry Slowik game 6.", "scores": {"first_break": [1800, 4000, 1000], "J_round": [4600, 6400, 2400], "DJ_round": [800, 12800, 4800], "final": [1600, 10600, 7800], "coryat": [12600, 13000, 4800]}}, "categories": {"jeopardy_round": ["JANUARY HOLIDAYS & OBSERVANCES", "JOINING THE TV CAST LATER", "WORLD OF FACTS", "JOE PARTY", "BASS", "\"ACK\" WORDS"], "double_jeopardy_round": ["A SLAYING SONG TONIGHT", "THIS & THAT", "AMERICAN HISTORY", "TUNNELS", "WORD ORIGINS", "STONE COLD JANE AUSTEN"], "final_jeopardy_round": ["ACTORS"]}, "contestants": {"1": {"player_name": "Jerry Slowik", "player_id": 8832}, "2": {"player_name": "Sarah Olson", "player_id": 8841}, "3": {"player_name": "Rachel Samberg", "player_id": 8840}}, "clues": {"J": {"(1, 1)": {"clue": "Burnt offerings in mid-January are part of \"Sending Off the Kitchen God Day\" for the 1.4 billion folks in this country", "clue_order_number": 9, "correct response": "China", "correct": "Sarah"}, "(2, 1)": {"clue": "Sam Waterston joined this show in 1994, 4 years after its debut; Sam stuck around for 16 more years", "clue_order_number": 4, "correct response": "Law & Order", "correct": "Jerry"}, "(3, 1)": {"clue": "This river has been eroding rock for about 6 million years, creating the Grand Canyon", "clue_order_number": 1, "correct response": "the Colorado", "correct": "Jerry"}, "(4, 1)": {"clue": "He married off his daughter Eunice to Sargent Shriver in 1953 at St. Patrick's with a cardinal officiating", "clue_order_number": 20, "correct response": "Joe Kennedy", "correct": "Jerry"}, "(5, 1)": {"clue": "Sure, there's a hook, but the bass seen here are really chasing this four-letter decoy", "clue_order_number": 12, "correct response": "lure", "correct": "Sarah"}, "(6, 1)": {"clue": "To destructively search a house", "clue_order_number": 13, "correct response": "ransack", "correct": "Jerry"}, "(1, 2)": {"clue": "January 3 is admission day in this state that celebrates being No. 49", "clue_order_number": 23, "correct response": "Alaska", "correct": "Jerry"}, "(2, 2)": {"clue": "Zou bisou bisou... latecomer Jessica Pare eventually married a Don on this drama", "clue_order_number": 5, "correct response": "Mad Men", "correct": "Sarah"}, "(3, 2)": {"clue": "Famous in World War II, Tobruk is a Mediterranean port in this North African country", "clue_order_number": 2, "correct response": "Libya", "Triple Stumper": true}, "(4, 2)": {"clue": "Tom has a party & Jerry tries to stop it in the short \"Saturday Evening Puss\", directed by William Hanna & him", "clue_order_number": 21, "correct response": "Joseph Barbera", "correct": "Jerry"}, "(5, 2)": {"clue": "Open wide & tell us the name of this game fish, the state fish of Georgia & Mississippi", "clue_order_number": 14, "correct response": "widemouth (or largemouth) bass", "correct": "Sarah"}, "(6, 2)": {"clue": "A quarterback sack is also one of these", "clue_order_number": 15, "correct response": "tackle", "correct": "Jerry"}, "(1, 3)": {"clue": "January 20 is Philately Day! Also, it's this big day, thanks to the 20th Amendment", "clue_order_number": 24, "correct response": "Inauguration Day", "Triple Stumper": true}, "(2, 3)": {"clue": "Later arrivals to this NBC medical drama included Mekhi Phifer, Parminder Nagra & John Stamos", "clue_order_number": 6, "correct response": "ER", "correct": "Sarah"}, "(3, 3)": {"clue": "Port Jackson is another name for this harbor, the principal port of New South Wales", "clue_order_number": 3, "correct response": "Sydney", "correct": "Sarah"}, "(4, 3)": {"clue": "The Victrola plays the tunes in Joseph Moncure March's \"The Wild Party\", a poem from this decade", "clue_order_number": 22, "correct response": "the 1920s", "correct": "Rachel"}, "(5, 3)": {"clue": "The markings of the rockfish give it the alternate name--this bass", "clue_order_number": 16, "correct response": "striped bass", "correct": "Sarah", "wrong0": "Jerry"}, "(6, 3)": {"clue": "In the '70s airline cockpits were stocked with maps of the Havana airport in preparation for this crime", "clue_order_number": 17, "correct response": "hijacking", "correct": "Jerry"}, "(1, 4)": {"clue": "We bet you know that on Jan, 27, Monte Carlo honors St. Devota, the patron saint of this principality", "clue_order_number": 25, "correct response": "Monaco", "correct": "Rachel"}, "(2, 4)": {"clue": "It took 3 years, but in 2004 we could report this drama introduced Lois Lane", "clue_order_number": 7, "correct response": "Smallville", "correct": "Jerry"}, "(3, 4)": {"clue": "In 1808 Prince John made this New World city the capital of the Portuguese empire", "clue_order_number": 10, "correct response": "Rio de Janeiro", "correct": "Sarah", "Daily Double": true, "Daily Double Wager": 600}, "(4, 4)": {"clue": "In 1886 this press lord was toastmaster at Delmonico's for a lavish Hungarian-American banquet", "clue_order_number": 27, "correct response": "Pulitzer", "correct": "Jerry"}, "(5, 4)": {"clue": "A 1967 tournament of 106 fishermen evolved into this \"classic\" tournament with a half million dollar prize to the winner", "clue_order_number": 29, "correct response": "Bassmaster Classic", "Triple Stumper": true}, "(6, 4)": {"clue": "It's a book section for an author's thanks to colleagues, family members et al.", "clue_order_number": 18, "correct response": "acknowledgment", "correct": "Sarah"}, "(1, 5)": {"clue": "Rice pudding is eaten on Thai Pongal, a January festival of this people of Sri Lanka & southern India", "clue_order_number": 26, "correct response": "Tamils", "Triple Stumper": true}, "(2, 5)": {"clue": "In 2006 Ed Helms joined in the \"documentary\" being \"filmed\" on this sitcom", "clue_order_number": 8, "correct response": "The Office", "correct": "Rachel"}, "(3, 5)": {"clue": "The Gran Sasso D'l'talia (\"Great Rock of Italy\") contains the highest point in this mountain range", "clue_order_number": 11, "correct response": "the Apennines", "correct": "Sarah"}, "(4, 5)": {"clue": "In 2009, the bicentennial of his death, this man who established the symphony form was celebrated all through Austria", "clue_order_number": 28, "correct response": "(Franz Joseph) Haydn", "correct": "Sarah"}, "(5, 5)": {"clue": "This \"stellar\" bass family lends its name to \"the most popular recreational sailboat in history\"", "clue_order_number": 30, "correct response": "sunfish", "Triple Stumper": true}, "(6, 5)": {"clue": "To intentionally put 5/8/13 on a document you're writing 3 months later on 8/5/13 is to do this", "clue_order_number": 19, "correct response": "backdating", "correct": "Jerry"}}, "DJ": {"(1, 1)": {"clue": "\"Murder by Numbers\" is the last track on this trio's album \"Synchronicity\"", "clue_order_number": 17, "correct response": "The Police", "correct": "Sarah"}, "(2, 1)": {"clue": "Currently the top 10 baby names for girls include Emma, Sophia Isabella & this; Ms. Newton-John was ahead of her time", "clue_order_number": 12, "correct response": "Olivia", "correct": "Rachel"}, "(4, 1)": {"clue": "Around 2180 B.C. a brick-lined walkway was built in Babylonia under this river to connect a palace & temple", "clue_order_number": 11, "correct response": "The Euphrates", "correct": "Rachel"}, "(5, 1)": {"clue": "This type of flimsy dressing (or should we say undressing?) gown comes from the French for \"neglected\"", "clue_order_number": 1, "correct response": "negligee", "correct": "Sarah"}, "(6, 1)": {"clue": "In 2013, a London lake got a 12-foot statue of this Austen character", "clue_order_number": 2, "correct response": "(Mr.) Darcy", "correct": "Sarah"}, "(1, 2)": {"clue": "He wrote & sang the song that includes the line \"I shot a man in Reno just to watch him die\"", "clue_order_number": 18, "correct response": "Johnny Cash", "correct": "Jerry"}, "(2, 2)": {"clue": "This state ranks 45th in population & 49th in area", "clue_order_number": 13, "correct response": "Delaware", "correct": "Rachel"}, "(3, 2)": {"clue": "(Jimmy of the Clue Crew presents the clue.)  With Missouri as its starting point, the Great Plains, the Rockies & the present state capitals of Salt Lake City, Carson City & Sacramento were on the route of this 19th century service", "clue_order_number": 29, "correct response": "the Pony Express", "correct": "Jerry"}, "(4, 2)": {"clue": "The Ahmed Hamdi tunnel, the first underwater tunnel to link Africa & Asia, runs from near Suez, Egypt to this peninsula", "clue_order_number": 22, "correct response": "Sinai", "correct": "Jerry"}, "(5, 2)": {"clue": "Greek for \"sun\" & \"turned toward\" give these flowers their name", "clue_order_number": 7, "correct response": "heliotrope", "correct": "Sarah"}, "(6, 2)": {"clue": "She's a wood... house! This title woman gets Harriet to reject a farmer's marriage proposal, but that turns out badly", "clue_order_number": 3, "correct response": "Emma", "correct": "Sarah"}, "(1, 3)": {"clue": "Merry Clayton was called to the studio in curlers to sing, \"rape, murder, it's just a shot away\" on this Stones tune", "clue_order_number": 19, "correct response": "\"Gimme Shelter\"", "correct": "Jerry"}, "(2, 3)": {"clue": "Contaminated needles are the most common cause of the C or chronic type of this liver disease", "clue_order_number": 14, "correct response": "hepatitis", "correct": "Jerry"}, "(3, 3)": {"clue": "In May 1857, 2 months after his famous Supreme Court decision, he was freed by Taylor Blow of St. Louis", "clue_order_number": 28, "correct response": "Dred Scott", "wrong0": "Jerry", "Daily Double": true}, "(4, 3)": {"clue": "The dangerous job of tunnel digger is also called \"sand\" this animal", "clue_order_number": 23, "correct response": "hog", "wrong0": "Sarah", "Triple Stumper": true}, "(5, 3)": {"clue": "The word for this crime against humanity was coined in the 1940s; it was used in the official indictment of Nazis in 1945", "clue_order_number": 8, "correct response": "genocide", "correct": "Rachel"}, "(6, 3)": {"clue": "Glenda Jackson brings this novel to life in audio book form", "clue_order_number": 4, "correct response": "Sense and Sensibility", "correct": "Sarah"}, "(1, 4)": {"clue": "His song \"Kim\", named for his ex-wife & the mother of his daughter, mentions double homicide & suicide", "clue_order_number": 20, "correct response": "Eminem", "correct": "Jerry"}, "(2, 4)": {"clue": "Film director Bernardo Bertolucci was born in this city that's famous for its ham & cheese", "clue_order_number": 15, "correct response": "Parma", "correct": "Rachel"}, "(3, 4)": {"clue": "With the consent of Massachusetts, this state was admitted to the union as part of the Missouri compromise in 1820", "clue_order_number": 26, "correct response": "Maine", "Triple Stumper": true}, "(4, 4)": {"clue": "On Nov. 27, 2000 this country's King Harald opened Laerdal tunnel, the world's longest road tunnel at 15.2 miles", "clue_order_number": 24, "correct response": "Norway", "Triple Stumper": true}, "(5, 4)": {"clue": "This type of fish is not a separate species but a Jewish delicacy whose name is Yiddish for \"stuffed fish\"", "clue_order_number": 9, "correct response": "gefilte fish", "correct": "Jerry"}, "(6, 4)": {"clue": "It's a day in the \"park\" & the price is right--the price being Fanny--in dealing with the Bertram family in this novel", "clue_order_number": 5, "correct response": "Mansfield Park", "correct": "Sarah"}, "(1, 5)": {"clue": "In a song by The Killers, \"there ain't no motive for this crime\" because this girl \"was a friend of mine\"", "clue_order_number": 21, "correct response": "Jenny", "Triple Stumper": true}, "(2, 5)": {"clue": "On July 9 members of this faith observe the anniversary of the martyrdom of the Bab", "clue_order_number": 16, "correct response": "Bah\u00e1\\'\u00ed", "Triple Stumper": true}, "(3, 5)": {"clue": "In 1911 Wisconsin's Victor Berger became the first congressman of this party of Eugene Debs", "clue_order_number": 25, "correct response": "Socialist", "correct": "Jerry"}, "(4, 5)": {"clue": "Connecting Midtown Manhattan with Weehawken, N.J., it's one of the world's busiest vehicular tunnels", "clue_order_number": 27, "correct response": "Lincoln Tunnel", "wrong0": "Jerry", "wrong1": "Rachel", "Triple Stumper": true}, "(5, 5)": {"clue": "This purplish red is named for a town in northern Italy", "clue_order_number": 10, "correct response": "magenta", "wrong0": "Jerry", "Daily Double": true}, "(6, 5)": {"clue": "This novel with a monastic title was sold to a publisher in 1803 but didn't appear until after Jane died in 1817", "clue_order_number": 6, "correct response": "Northanger Abbey", "correct": "Sarah"}}, "FJ": {"(0, 0)": {"clue": "In the '50s he won a Tony for Best Supporting Actor in a Musical & a Best Actor Oscar for playing the same role, a monarch"}}}}