{"info": {"show number": 7382, "date": "2016-10-18", "game_id": 5433, "game_comments": "", "scores": {"first_break": [3800, 200, 2800], "J_round": [5400, 200, 5000], "DJ_round": [18000, 11400, 14200], "final": [28431, 15200, 2200], "coryat": [13400, 11000, 14200]}}, "categories": {"jeopardy_round": ["I'M A WHEEL WATCHER", "PLANET EARTH", "WHAT CAN YOU BUY FOR A BUCK?", "U.S. HISTORY", "L.A. TELEVISION", "T(4 LETTERS)T"], "double_jeopardy_round": ["AUTHORS WITH PRESIDENTIAL NAMES", "2-WORD COUNTRIES", "ROCK \"ME\"", "DOME, DOME ON THE RANGE", "WHERE SELDOM IS HEARD", "A DISCOURAGING WORD"], "final_jeopardy_round": ["FUNNYMEN"]}, "contestants": {"1": {"player_name": "Shannon Dillmore", "player_id": 10962}, "2": {"player_name": "Jeremy Zarowitz", "player_id": 10961}, "3": {"player_name": "Anne Exler", "player_id": 10960}}, "clues": {"J": {"(1, 1)": {"clue": "This numerical slang term for a tractor-trailer truck comes from what goes on its many axles", "clue_order_number": 23, "correct response": "an 18-wheeler", "correct": "Shannon"}, "(2, 1)": {"clue": "It's the name used for any half of the globe", "clue_order_number": 19, "correct response": "hemisphere", "correct": "Anne"}, "(3, 1)": {"clue": "A new one of these every month from the Dollar Shave Club", "clue_order_number": 11, "correct response": "a razor", "correct": "Shannon"}, "(5, 1)": {"clue": "Throughout the '90s, David Hasselhoff & company kept L.A. County beaches safe on this TV series", "clue_order_number": 16, "correct response": "Baywatch", "correct": "Jeremy"}, "(6, 1)": {"clue": "The object in competition shooting", "clue_order_number": 4, "correct response": "a target", "correct": "Shannon"}, "(1, 2)": {"clue": "Huck Finn could tell you this type of steamer once churned up & down the Mississippi", "clue_order_number": 24, "correct response": "a paddlewheel", "correct": "Anne"}, "(2, 2)": {"clue": "Burning coal & oil in the Industrial Age has produced this, atomic No. 6--mix it with oxygen & you get a greenhouse gas", "clue_order_number": 18, "correct response": "carbon", "correct": "Jeremy"}, "(3, 2)": {"clue": "A travel-sized bottle of this from Purell", "clue_order_number": 12, "correct response": "hand sanitizer", "correct": "Jeremy"}, "(4, 2)": {"clue": "2 weeks after 9/11, a CIA team entered this country to prep our invasion", "clue_order_number": 29, "correct response": "Afghanistan", "correct": "Shannon"}, "(5, 2)": {"clue": "His trusty agent & close circle of friends helped film star Vince Chase navigate L.A. on this show", "clue_order_number": 17, "correct response": "Entourage", "correct": "Jeremy"}, "(6, 2)": {"clue": "It's the force that propels a plane", "clue_order_number": 6, "correct response": "thrust", "correct": "Anne"}, "(1, 3)": {"clue": "With a spin of the wheel in this casino game, you can win $350 with a $10 bet", "clue_order_number": 3, "correct response": "roulette", "correct": "Anne"}, "(2, 3)": {"clue": "This dark, organic substance found in soil & formed from decaying matter is good for plants; some might try to eat it with pita", "clue_order_number": 1, "correct response": "humus", "correct": "Shannon", "Daily Double": true}, "(3, 3)": {"clue": "At one of the dollar stores, you can get an 8-digit desktop or pocket one of these", "clue_order_number": 20, "correct response": "a calculator", "correct": "Anne"}, "(4, 3)": {"clue": "The 1912 platform of this short-lived political party had all the antlers, like direct election of U.S. senators", "clue_order_number": 13, "correct response": "Bull Moose", "correct": "Jeremy"}, "(5, 3)": {"clue": "As inner city L.A. cop Vic Mackey on \"The Shield\", this actor wasn't above breaking a few rules", "clue_order_number": 26, "correct response": "(Michael) Chiklis", "correct": "Jeremy"}, "(6, 3)": {"clue": "Jamal Al-Fayeed was the title despot on this FX drama", "clue_order_number": 7, "correct response": "Tyrant", "correct": "Shannon"}, "(1, 4)": {"clue": "It's a wheeled platform with a mounted camera on it used to make a tracking shot", "clue_order_number": 5, "correct response": "a dolly", "correct": "Anne"}, "(2, 4)": {"clue": "(Sarah of the Clue Crew gives the clue from the USS Intrepid in Norfolk, VA.)  The Concorde cruised at 60,000 feet, high enough for its 100 passengers to see this phenomenon, which at just 8 inches per mile is invisible from lower altitudes", "clue_order_number": 2, "correct response": "the curvature of the Earth", "Triple Stumper": true}, "(3, 4)": {"clue": "A Crunchtada Tostada or grilled chicken taco from this chain", "clue_order_number": 21, "correct response": "Del Taco", "wrong0": "Jeremy", "Triple Stumper": true}, "(4, 4)": {"clue": "In June 1877 a war began between this tribe & the U.S. in Idaho, ending when federal troops captured Chief Joseph", "clue_order_number": 14, "correct response": "the Nez Perce", "wrong0": "Jeremy", "Triple Stumper": true}, "(5, 4)": {"clue": "As this title fixer for the L.A. rich & famous, Liev Schreiber seems to solve everyone's problems but his own", "clue_order_number": 27, "correct response": "Ray Donovan", "wrong0": "Jeremy", "Triple Stumper": true}, "(6, 4)": {"clue": "A small tower in a fortress", "clue_order_number": 8, "correct response": "a turret", "correct": "Shannon"}, "(1, 5)": {"clue": "Often found on the bottom of heavy furniture, it's a wheel that swivels in order to help in moving large objects", "clue_order_number": 25, "correct response": "a caster", "Triple Stumper": true}, "(2, 5)": {"clue": "These 5 letters follow \"rock\" or \"mud\" in a type of event that killed thousands in the 2008 Sichuan earthquake", "clue_order_number": 10, "correct response": "slide", "correct": "Anne"}, "(3, 5)": {"clue": "For your Kindle a \"megapack\" of 15 classic stories in this genre by Philip K. Dick", "clue_order_number": 22, "correct response": "science fiction", "correct": "Anne"}, "(4, 5)": {"clue": "Regular passenger transatlantic air service began in June 1939 when this company's Dixie Clipper flew from N.Y. to Portugal", "clue_order_number": 15, "correct response": "Pan Am", "Triple Stumper": true}, "(5, 5)": {"clue": "5 decades apart, we spent time on this title road, at \"77\" & in \"Studio 60\"", "clue_order_number": 28, "correct response": "the Sunset Strip", "correct": "Shannon"}, "(6, 5)": {"clue": "There's only 1 vowel in this word, to oppose a plan successfully", "clue_order_number": 9, "correct response": "thwart", "correct": "Shannon"}}, "DJ": {"(1, 1)": {"clue": "In 1809 he published \"A History of New York\" under the pen name Diedrich Knickerbocker", "clue_order_number": 22, "correct response": "Washington Irving", "Triple Stumper": true}, "(2, 1)": {"clue": "One of this country's major exports is known as K-pop, like the hit \"Gangnam Style\"", "clue_order_number": 21, "correct response": "South Korea", "correct": "Shannon"}, "(3, 1)": {"clue": "\"You have made my life complete, and I love you so\" says this Elvis hit", "clue_order_number": 5, "correct response": "\"Love Me Tender\"", "correct": "Shannon"}, "(4, 1)": {"clue": "2 main Muslim holy sites were built on the Temple Mount after the fall of the Second Temple: the Al-Aqsa Mosque & this one", "clue_order_number": 28, "correct response": "the Dome of the Rock", "wrong0": "Shannon", "Triple Stumper": true}, "(5, 1)": {"clue": "\"Sure, Maui is nice, but I'm moving to\" this Russian region covering nearly 5 million sq. miles; \"livable warmth is so last year\"", "clue_order_number": 14, "correct response": "Siberia", "correct": "Anne"}, "(6, 1)": {"clue": "This bovine term means to bully, & we can wait 'til it comes home for you to respond", "clue_order_number": 15, "correct response": "cow", "correct": "Anne"}, "(1, 2)": {"clue": "Not John but Anne is the first name of this author of \"Dinner at the Homesick Restaurant\"", "clue_order_number": 23, "correct response": "(Anne) Tyler", "correct": "Anne"}, "(2, 2)": {"clue": "It occupies most of the world's largest peninsula", "clue_order_number": 10, "correct response": "Saudi Arabia", "correct": "Shannon", "Daily Double": true}, "(3, 2)": {"clue": "\"But she wears short skirts, I wear T-shirtsShe's cheer captain and I'm on the bleachers\" in this Taylor Swift tune", "clue_order_number": 6, "correct response": "\"You Belong With Me\"", "correct": "Anne"}, "(4, 2)": {"clue": "This concert, NFL & Atlanta Olympics venue has 4 A/C units totaling 5,000 tons", "clue_order_number": 29, "correct response": "the Georgia Dome", "Triple Stumper": true}, "(5, 2)": {"clue": "This \"Omnimedia\" style maven: \"Whether making a quilt or preparing filet mignon, do it any way you want!  It doesn't matter!\"", "clue_order_number": 13, "correct response": "Martha Stewart", "correct": "Shannon"}, "(6, 2)": {"clue": "Preceding \"upon\", it means to look disapprovingly; now turn that smile upside down!", "clue_order_number": 16, "correct response": "frown", "correct": "Jeremy"}, "(1, 3)": {"clue": "Her haunting short story \"The Lottery\" first appeared in the New Yorker in 1948", "clue_order_number": 4, "correct response": "(Shirley) Jackson", "correct": "Anne"}, "(2, 3)": {"clue": "Independence for this country seen here was unfortunately followed by civil war", "clue_order_number": 1, "correct response": "South Sudan", "correct": "Jeremy"}, "(3, 3)": {"clue": "4-word title of the song in which \"Freedom's just another word for nothin' left to lose\"", "clue_order_number": 7, "correct response": "\"Me And Bobby McGee\"", "correct": "Jeremy"}, "(4, 3)": {"clue": "Stephen King wrote in this novel, \"It was whole, then it was in 2 pieces... as if an invisible guillotine blade had dropped\"", "clue_order_number": 17, "correct response": "Under the Dome", "correct": "Jeremy"}, "(5, 3)": {"clue": "From this Conn. school: \"Now that our endowment has reached $25.6 bil. in 2015, let's put it all on red for one roulette spin\"", "clue_order_number": 8, "correct response": "Yale", "correct": "Jeremy"}, "(6, 3)": {"clue": "To dull one's spirits, or to moisten a cloth", "clue_order_number": 19, "correct response": "dampen", "correct": "Shannon"}, "(1, 4)": {"clue": "This title of Stephen Carter's Cuban Missile Crisis thriller means a secret avenue of communication between nations", "clue_order_number": 3, "correct response": "Back Channel", "correct": "Shannon"}, "(2, 4)": {"clue": "They are the 2 2-word nations in Central America", "clue_order_number": 11, "correct response": "Costa Rica & El Salvador", "correct": "Anne", "wrong0": "Shannon"}, "(3, 4)": {"clue": "\"When the night has come and the land is dark\", I'll be okay if you do this", "clue_order_number": 12, "correct response": "\"Stand By Me\"", "correct": "Shannon"}, "(4, 4)": {"clue": "A shell structure with a frame of tubing connected into hexagons, pentagons & triangles is this type of dome", "clue_order_number": 2, "correct response": "geodesic", "correct": "Jeremy", "Daily Double": true}, "(5, 4)": {"clue": "This junior senator from Florida: \"You know who has a lot of great ideas? Hillary Clinton\"", "clue_order_number": 25, "correct response": "(Marco) Rubio", "correct": "Jeremy"}, "(6, 4)": {"clue": "Change the prefix in persuade & you get this 8-letter opposite", "clue_order_number": 20, "correct response": "dissuade", "correct": "Shannon"}, "(1, 5)": {"clue": "John Kennedy Toole took this novel title from a quote by Jonathan Swift", "clue_order_number": 9, "correct response": "A Confederacy of Dunces", "correct": "Shannon"}, "(2, 5)": {"clue": "The name of this West African country may refer to the shape of nearby hills resembling a certain beast", "clue_order_number": 27, "correct response": "Sierra Leone", "correct": "Shannon"}, "(3, 5)": {"clue": "Police song that says, \"Her friends are so jealous, you know how bad girls get\"", "clue_order_number": 18, "correct response": "\"Don\\'t Stand So Close To Me\"", "correct": "Anne"}, "(5, 5)": {"clue": "\"Sure, I'll have a 6th helping of\" this 4-letter veggie with loose, curly leaves (actually, that may be heard in L.A. quite often)", "clue_order_number": 26, "correct response": "kale", "correct": "Jeremy"}, "(6, 5)": {"clue": "Negative altitude in astronomy, or a period of economic woe", "clue_order_number": 24, "correct response": "depression", "correct": "Anne", "wrong0": "Shannon"}}, "FJ": {"(0, 0)": {"clue": "He's won 4 Emmys, 3 Grammys, an Oscar & 3 Tonys, & 3 of his films rank on AFI's list of funniest movies of all time"}}}}