{"info": {"show number": 3761, "date": "2001-01-01", "game_id": 2245, "game_comments": "First show of the 21st century.", "scores": {"first_break": [2000, 900, 400], "J_round": [2500, 1700, 1300], "DJ_round": [8700, 5700, 2500], "final": [5999, 5700, 0], "coryat": [8700, 6000, 2500]}}, "categories": {"jeopardy_round": ["NEW YEAR'S DAY", "GEOGRAPH\"IA\"", "EPITAPHS", "1802", "BROADWAY DEBUTS", "RHYME TIME"], "double_jeopardy_round": ["LITERATURE", "CHEMISTRY", "ECONOMICS", "PHYSICS", "\"PEACE\"", "MADISON & PHYSIOLOGY"], "final_jeopardy_round": ["CELEBRITY WOMEN"]}, "contestants": {"1": {"player_name": "Richard Kolostian", "player_id": 4496}, "2": {"player_name": "Mike Currie", "player_id": 4513}, "3": {"player_name": "Sherry Huiner", "player_id": 4512}}, "clues": {"J": {"(1, 1)": {"clue": "The Tournament of Roses Parade & the Rose Bowl are held in this city on New Year's Day", "clue_order_number": 11, "correct response": "Pasadena", "correct": "Richard"}, "(2, 1)": {"clue": "Victoria is the capital of this Canadian province", "clue_order_number": 1, "correct response": "British Columbia", "correct": "Mike"}, "(3, 1)": {"clue": "\"Quoth the raven nevermore\"", "clue_order_number": 6, "correct response": "Edgar Allan Poe", "correct": "Mike"}, "(4, 1)": {"clue": "In 1802, after he'd been in office for a year, the first article on his involvement with Sally Hemings was published", "clue_order_number": 16, "correct response": "Thomas Jefferson", "correct": "Sherry"}, "(5, 1)": {"clue": "In 1999 she was dishing with Regis in the daytime & \"Putting It Together\" on Broadway at night", "clue_order_number": 21, "correct response": "Kathie Lee Gifford", "correct": "Sherry"}, "(6, 1)": {"clue": "A noisy cumulonimbus", "clue_order_number": 26, "correct response": "Loud cloud", "correct": "Mike"}, "(1, 2)": {"clue": "Also called the Feast of Trumpets, this holiday, the Jewish New Year, is celebrated on the first 2 days of Tishri", "clue_order_number": 12, "correct response": "Rosh Hashanah", "correct": "Richard"}, "(2, 2)": {"clue": "In 1976 Nadia Comaneci scored perfect 10s & Olympic gold for this country", "clue_order_number": 2, "correct response": "Romania", "correct": "Mike"}, "(3, 2)": {"clue": "\"Everybody loves somebody sometime\"", "clue_order_number": 7, "correct response": "Dean Martin", "correct": "Richard"}, "(4, 2)": {"clue": "Incorporated as a town in 1802; made capital of the Michigan Territory in 1805; burned down the same year", "clue_order_number": 17, "correct response": "Detroit", "wrong0": "Mike", "Triple Stumper": true}, "(5, 2)": {"clue": "Robert Goulet debuted as Lancelot in this 1960 show; in 1993 he brought it back to B'way & played King Arthur", "clue_order_number": 22, "correct response": "\"Camelot\"", "correct": "Mike"}, "(6, 2)": {"clue": "A grizzly that isn't hip", "clue_order_number": 27, "correct response": "Square bear", "correct": "Richard"}, "(1, 3)": {"clue": "It's the palindromic name for the Vietnamese New Year", "clue_order_number": 13, "correct response": "Tet", "correct": "Richard"}, "(2, 3)": {"clue": "George Washington helped lay out the streets of this Virginia city", "clue_order_number": 3, "correct response": "Alexandria", "wrong0": "Mike", "Daily Double": true, "Daily Double Wager": 500}, "(3, 3)": {"clue": "\"Faithful to the cause of Prohibition -- she hath done what she could\"", "clue_order_number": 8, "correct response": "Carrie Nation", "correct": "Richard"}, "(4, 3)": {"clue": "In his \"Heiligenstadt Tastament\", Beethoven lamented over his loss of this", "clue_order_number": 18, "correct response": "Hearing", "correct": "Mike"}, "(5, 3)": {"clue": "The sexy 1969 musical \"Canterbury Tales\" marked the Broadway debut of this perky star seen here", "clue_order_number": 23, "correct response": "Sandy Duncan", "correct": "Sherry"}, "(6, 3)": {"clue": "An adorable wind instrument", "clue_order_number": 28, "correct response": "Cute flute", "correct": "Richard"}, "(1, 4)": {"clue": "In the Middle Ages New Year's Day was observed on March 25, this feast day that celebrates Mary's visit from Gabriel", "clue_order_number": 14, "correct response": "Annunciation", "correct": "Sherry", "wrong0": "Mike"}, "(2, 4)": {"clue": "Lake Titicaca is on the border of Peru & this country", "clue_order_number": 4, "correct response": "Bolivia", "correct": "Mike"}, "(3, 4)": {"clue": "\"That's all folks\"", "clue_order_number": 9, "correct response": "Mel Blanc", "correct": "Richard"}, "(4, 4)": {"clue": "French mining engineer Albert Matieu-Favier suggested building a tunnel under this", "clue_order_number": 19, "correct response": "English Channel", "correct": "Sherry", "wrong0": "Richard"}, "(5, 4)": {"clue": "Keith Carradine was a teenager when he was cast in this \"American Tribal Love-Rock\" musical in 1968", "clue_order_number": 24, "correct response": "\"Hair\"", "correct": "Richard"}, "(6, 4)": {"clue": "A hilarious little rabbit", "clue_order_number": 29, "correct response": "Funny bunny", "correct": "Mike"}, "(1, 5)": {"clue": "The Mummers New Year's Day Parade in this city started officially in 1901", "clue_order_number": 15, "correct response": "Philadelphia", "correct": "Mike"}, "(2, 5)": {"clue": "This country is moving its capital to Dodoma from Dar es Salaam", "clue_order_number": 5, "correct response": "Tanzania", "correct": "Mike"}, "(3, 5)": {"clue": "Died 1789:\"His spirit is in Vermont now\"", "clue_order_number": 10, "correct response": "Ethan Allen", "correct": "Richard"}, "(4, 5)": {"clue": "Napoleon established this \"Legion\" as an Order of Merit in 1802", "clue_order_number": 20, "correct response": "Legion of Honor (Legion d\\'honneur)", "wrong0": "Richard", "Triple Stumper": true}, "(5, 5)": {"clue": "My cousin Vinny saw her in the 1998 revival of \"Wait Until Dark\", with Quentin Tarantino as her stalker", "clue_order_number": 25, "correct response": "Marisa Tomei", "correct": "Richard"}, "(6, 5)": {"clue": "A fake foot covering", "clue_order_number": 30, "correct response": "a mock sock", "Triple Stumper": true}}, "DJ": {"(1, 1)": {"clue": "This Nobel Prize winner dedicated \"The Waste Land\" to fellow poet Ezra Pound", "clue_order_number": 1, "correct response": "T.S. Eliot", "correct": "Sherry"}, "(2, 1)": {"clue": "He said about his romance with Soon-Yi, \"The heart wants what it wants\"", "clue_order_number": 25, "correct response": "Woody Allen", "correct": "Sherry"}, "(3, 1)": {"clue": "In the U.S., the total of this type of debt has \"charged\" ahead to around $585 billion", "clue_order_number": 4, "correct response": "Credit card debt", "correct": "Sherry"}, "(4, 1)": {"clue": "Transonic speed is about 741 MPH at sea level; supersonic is faster & this is the term for slower", "clue_order_number": 17, "correct response": "Subsonic", "correct": "Mike"}, "(5, 1)": {"clue": "Black's Law Dictionary defines it as a violation of the public tranquility & order", "clue_order_number": 11, "correct response": "Disturbing/breach of the peace", "correct": "Sherry"}, "(6, 1)": {"clue": "Both men who held this post under James Madison, George Clinton & Elbridge Gerry, died in office", "clue_order_number": 16, "correct response": "Vice president", "correct": "Mike"}, "(1, 2)": {"clue": "His \"Dr. Zhivago\" aroused so much opposition in the Soviet Union that he said \"Nyet\" to the Nobel Prize in 1958", "clue_order_number": 2, "correct response": "Boris Pasternak", "correct": "Mike"}, "(2, 2)": {"clue": "Joe Lieberman's beloved, or the Women's Zionist Organization of America", "clue_order_number": 26, "correct response": "Hadassah", "correct": "Richard"}, "(3, 2)": {"clue": "The CPI is the Consumer Price Index & the PPI is this", "clue_order_number": 5, "correct response": "Producer Price Index", "correct": "Richard"}, "(4, 2)": {"clue": "With wavelengths between those of visible light & microwaves, they come from the sun & heat the Earth", "clue_order_number": 18, "correct response": "Infrared waves", "correct": "Mike"}, "(5, 2)": {"clue": "George Clooney & Nicole Kidman team up against terrorists in this 1997 movie", "clue_order_number": 12, "correct response": "The Peacemaker", "correct": "Mike"}, "(6, 2)": {"clue": "Neurons don't weigh much; why, there are billions of them in this roughly 3-pound organ", "clue_order_number": 20, "correct response": "Brain", "correct": "Mike"}, "(1, 3)": {"clue": "In 1953 this British politician won the Nobel Prize for his biographical & historical works & for his oratory", "clue_order_number": 3, "correct response": "Winston Churchill", "correct": "Richard"}, "(2, 3)": {"clue": "She had high school chemistry with Peter Jacobson, whom she married in 1978 & later helped create \"The Nanny\"", "clue_order_number": 27, "correct response": "Fran Drescher", "correct": "Richard"}, "(3, 3)": {"clue": "Rude term for the unfair trade practice of selling goods below cost in a foreign market", "clue_order_number": 6, "correct response": "Dumping", "correct": "Mike"}, "(4, 3)": {"clue": "5-letter word that precedes \"isotope\" in a term for isotopes like strontium-90 & cobalt-60", "clue_order_number": 19, "correct response": "Radio", "correct": "Richard"}, "(5, 3)": {"clue": "Leviticus 7 discusses these \"unto the Lord\", saying they may include unleavened cakes", "clue_order_number": 13, "correct response": "Peace offerings", "correct": "Mike"}, "(6, 3)": {"clue": "Madison pooh-poohed that he was \"The Father of\" this; he said it was \"The work of many heads and many hands\"", "clue_order_number": 21, "correct response": "The Constitution", "correct": "Sherry"}, "(1, 4)": {"clue": "He was no \"Stranger\" to the Nobel Prize for Literature, winning in 1957", "clue_order_number": 7, "correct response": "Albert Camus", "wrong0": "Mike", "Daily Double": true}, "(2, 4)": {"clue": "Hearts were broken when Sarah Michelle Gellar took up with this \"She's All That\" star", "clue_order_number": 28, "correct response": "Freddie Prinze, Jr.", "correct": "Richard"}, "(3, 4)": {"clue": "Seen here, it's what's moving the chess piece, & also the name of an economics term", "clue_order_number": 9, "correct response": "\"Invisible Hand\"", "correct": "Richard"}, "(4, 4)": {"clue": "It's the tendency of an object to float, or the upward pressure of fluid in an object", "clue_order_number": 23, "correct response": "Buoyancy", "correct": "Mike", "Daily Double": true}, "(5, 4)": {"clue": "In Handel's \"Messiah\", his name shall be called \"The Mighty God, the Everlasting Father\", this", "clue_order_number": 14, "correct response": "\"Prince of Peace\"", "correct": "Sherry"}, "(6, 4)": {"clue": "After leaving the presidency Madison returned to his estate named this", "clue_order_number": 22, "correct response": "Montpelier", "correct": "Mike"}, "(1, 5)": {"clue": "A poem by this 1923 Nobel Prize winner is heard here:(\"I will arise and go now, and go to Innisfree, And a small cabin build there, of clay and wattles made\")", "clue_order_number": 8, "correct response": "William Butler Yeats", "wrong0": "Sherry", "Triple Stumper": true}, "(2, 5)": {"clue": "In 2000 she married David Bale, father of actor Christian, but we assume she's still \"Ms.\", not Mrs.", "clue_order_number": 29, "correct response": "Gloria Steinem", "correct": "Richard", "wrong0": "Mike"}, "(3, 5)": {"clue": "5-letter word for temporary paper money issued in economic emergencies", "clue_order_number": 10, "correct response": "Scrip", "correct": "Richard"}, "(4, 5)": {"clue": "Found after \"de\" in a term meaning to demagnetize, it's the last name of German mathematician Karl", "clue_order_number": 24, "correct response": "Gauss", "Triple Stumper": true}, "(5, 5)": {"clue": "In 1963 it was Khrushchev's professed policy of tolerance in his dealings with the West", "clue_order_number": 15, "correct response": "Peaceful coexistence", "Triple Stumper": true}}, "FJ": {"(0, 0)": {"clue": "She said, \"The reason I'm not a nun is...you can't take your own name...I have the most holy name a woman can have\""}}}}