{"info": {"show number": 5884, "date": "2010-03-25", "game_id": 3351, "game_comments": "Regina Robbins game 3.", "scores": {"first_break": [2200, 1400, 3800], "J_round": [3400, 4400, 5200], "DJ_round": [10600, 10400, 10800], "final": [21200, 20600, 399], "coryat": [10600, 10400, 11800]}}, "categories": {"jeopardy_round": ["THE LEAGUE OF NATIONS", "WEAK RHYMES", "PHYSICS QUIZ", "MY NAME IS GEORGE", "I'M UNEMPLOYED", "& I LIVE WITH MY PARENTS"], "double_jeopardy_round": ["HOW'S YOUR CONSTITUTION?", "ATHLETIC EYEWEAR", "\"O\", 'BAMA", "PLANES, TRAINS & AUTOMOBILES", "NAME THE POET", "DICT. ABBREV."], "final_jeopardy_round": ["U.S. TOURISM"]}, "contestants": {"1": {"player_name": "Regina Robbins", "player_id": 6757}, "2": {"player_name": "Susan Malmo", "player_id": 6761}, "3": {"player_name": "Sean Burns", "player_id": 6760}}, "clues": {"J": {"(1, 1)": {"clue": "The Palace of Nations, the League's headquarters, was built on land next to this Swiss lake", "clue_order_number": 11, "correct response": "Geneva", "correct": "Regina"}, "(2, 1)": {"clue": "A computer nerd", "clue_order_number": 1, "correct response": "a geek", "correct": "Sean"}, "(3, 1)": {"clue": "In air at a temperature of 32 degrees Fahrenheit, it travels 1,087 feet per second", "clue_order_number": 14, "correct response": "sound", "correct": "Sean"}, "(4, 1)": {"clue": "This musician & 3 other lads won an Oscar for Best Music, Original Song Score for 1970's \"Let It Be\"", "clue_order_number": 6, "correct response": "George Harrison", "correct": "Susan"}, "(5, 1)": {"clue": "She finished her first novel about a magical 11-year-old orphan while she was an unemployed teacher in Edinburgh", "clue_order_number": 18, "correct response": "(J.K.) Rowling", "correct": "Susan"}, "(6, 1)": {"clue": "I'm sure Mom won't mind; I had the last chicken & garlic box of this \"San Francisco treat\"", "clue_order_number": 23, "correct response": "Rice-A-Roni", "correct": "Sean"}, "(1, 2)": {"clue": "The League was dissolved in April of this year; the United Nations charter had been ratified the previous October", "clue_order_number": 12, "correct response": "1946", "correct": "Susan"}, "(2, 2)": {"clue": "To run naked in a public place", "clue_order_number": 2, "correct response": "to streak", "correct": "Regina"}, "(3, 2)": {"clue": "When this man developed his temperature scale in 1742, he set it where water boils at 0 & freezes at 100 degrees", "clue_order_number": 15, "correct response": "Celsius", "correct": "Sean", "wrong0": "Regina"}, "(4, 2)": {"clue": "Meet this TV guy... his boy Elroy... daughter Judy... Jane, his wife--he never could \"stop this crazy thing!\"", "clue_order_number": 7, "correct response": "George Jetson", "correct": "Sean"}, "(5, 2)": {"clue": "The website of the California DWC, the Division of Workers' this, has a link to \"when I get hurt on the job\"", "clue_order_number": 19, "correct response": "Compensation", "correct": "Regina"}, "(6, 2)": {"clue": "Uh, Dad? I kinda crashed your Land Cruiser SUV made by this car co.; the 2009 model starts at nearly $65,000; I'm a little short", "clue_order_number": 25, "correct response": "Toyota", "wrong0": "Susan", "Triple Stumper": true}, "(1, 3)": {"clue": "When established, the League had only 2 nations from Africa: South Africa & this one founded in 1847", "clue_order_number": 13, "correct response": "Liberia", "correct": "Sean"}, "(2, 3)": {"clue": "The most striking feature on a puffin is this colorful body part", "clue_order_number": 3, "correct response": "the beak", "correct": "Sean"}, "(3, 3)": {"clue": "(Kelly of the Clue Crew drops a cork and a glass marble into two separate bowls of water.)  If an object floats, it displaces water equal to its mass; if it sinks, it displaces water equal to this", "clue_order_number": 16, "correct response": "its volume", "correct": "Sean", "Daily Double": true}, "(4, 3)": {"clue": "In 1919 this composer wrote his first successful popular song, \"Swanee\"", "clue_order_number": 8, "correct response": "George Gershwin", "correct": "Sean"}, "(5, 3)": {"clue": "The nation's unemployment rate was 25% when FDR took his first presidential oath of office in this year", "clue_order_number": 20, "correct response": "1933", "correct": "Susan", "wrong0": "Sean"}, "(6, 3)": {"clue": "Maaaaaa! We're out of this bathroom tissue Mr. Whipple always said to \"Please don't squeeze\"! Maaaaaa!", "clue_order_number": 28, "correct response": "the Charmin", "correct": "Sean"}, "(1, 4)": {"clue": "In March 1920 the U.S. Senate did not ratify this treaty that created the League of Nations", "clue_order_number": 26, "correct response": "the Treaty of Versailles", "correct": "Regina"}, "(2, 4)": {"clue": "Tall East Indian timber tree with durable, hard wood", "clue_order_number": 4, "correct response": "the teak", "correct": "Susan"}, "(3, 4)": {"clue": "Alliterative term for the state of a body in midair acted on by nothing but gravity", "clue_order_number": 17, "correct response": "free-falling", "correct": "Susan"}, "(4, 4)": {"clue": "His reported salary for co-writing, directing & starring in \"Good Night, and Good Luck\" was $1", "clue_order_number": 9, "correct response": "George Clooney", "correct": "Sean"}, "(5, 4)": {"clue": "\"On\" this state, \"On\" this state that adopted the first unemployment insurance law in the U.S.! Fight on for her fame!", "clue_order_number": 21, "correct response": "Wisconsin", "correct": "Susan"}, "(1, 5)": {"clue": "In 1922 the League's World Court held its first session in this city", "clue_order_number": 27, "correct response": "The Hague", "Triple Stumper": true}, "(2, 5)": {"clue": "Originally referring to smoke, it means to smell offensively bad", "clue_order_number": 5, "correct response": "to reek", "correct": "Regina"}, "(3, 5)": {"clue": "Named for the British physicist, Hawking radiation is a weak force emitted by these", "clue_order_number": 24, "correct response": "black holes", "Triple Stumper": true}, "(4, 5)": {"clue": "This singer guested as himself in a 1986 episode of \"The A-Team\"; do you really want to hurt him & not know his name?", "clue_order_number": 10, "correct response": "Boy George", "correct": "Regina"}, "(5, 5)": {"clue": "In 2007 CBS Radio fired this broadcaster after his controversial comments about the women's hoops team at Rutgers", "clue_order_number": 22, "correct response": "(Don) Imus", "correct": "Susan"}}, "DJ": {"(1, 1)": {"clue": "Article VI says no test of this can be required for any public office (the Brits had had trouble with test acts)", "clue_order_number": 6, "correct response": "religion", "Triple Stumper": true}, "(2, 1)": {"clue": "In 2008 Cuba's bespectacled Dayron Robles leaped to glory with a world record in the 110-meter these", "clue_order_number": 26, "correct response": "the hurdles", "correct": "Sean"}, "(3, 1)": {"clue": "Fittingly, this juicy-sounding \"Beach\" is right next to the Florida border", "clue_order_number": 9, "correct response": "Orange Beach", "wrong0": "Regina", "Triple Stumper": true}, "(4, 1)": {"clue": "At the Smithsonian you can see this plane in which Charles Lindbergh made his historic flight across the Atlantic", "clue_order_number": 8, "correct response": "the Spirit of St. Louis", "correct": "Susan"}, "(5, 1)": {"clue": "\"Fleas\": \"Adam had 'em\"", "clue_order_number": 1, "correct response": "(Ogden) Nash", "correct": "Sean"}, "(6, 1)": {"clue": "A part of speech: prep.", "clue_order_number": 13, "correct response": "a preposition", "correct": "Susan"}, "(1, 2)": {"clue": "The 8th amendment told the courts they couldn't impose excessive fines nor require excessive amounts of this", "clue_order_number": 7, "correct response": "bail", "wrong0": "Regina", "Triple Stumper": true}, "(2, 2)": {"clue": "After wearing specs throughout an illustrious PGA career, Tom Kite had this surgery in 1998", "clue_order_number": 27, "correct response": "Lasik", "correct": "Sean"}, "(3, 2)": {"clue": "This city's name is the singular version of a mountain range in Arkansas", "clue_order_number": 10, "correct response": "Ozark", "correct": "Sean"}, "(4, 2)": {"clue": "The Ann Rutledge, a train that ran between Chicago & Kansas City, was named for an early love of this president", "clue_order_number": 22, "correct response": "Abraham Lincoln", "wrong0": "Susan", "Triple Stumper": true}, "(5, 2)": {"clue": "\"Day after day, day after day, / We stuck, no breath or motion; / As idle as a painted ship / Upon a painted ocean\"", "clue_order_number": 2, "correct response": "Coleridge", "correct": "Susan"}, "(6, 2)": {"clue": "Another way to shorten: contr.", "clue_order_number": 16, "correct response": "a contraction", "correct": "Regina"}, "(1, 3)": {"clue": "Article III is specifically concerned with the establishment of this branch of government", "clue_order_number": 11, "correct response": "the judiciary", "Triple Stumper": true}, "(2, 3)": {"clue": "He's the late, graceful American star athlete seen here", "clue_order_number": 28, "correct response": "Arthur Ashe", "correct": "Susan"}, "(3, 3)": {"clue": "Population 100, it shares its name with a Tennessee city famous in atomic history", "clue_order_number": 14, "correct response": "Oak Ridge", "correct": "Susan", "Daily Double": true}, "(4, 3)": {"clue": "In 2008 Chevy offered a special 50th anniversary edition of this classic sedan", "clue_order_number": 23, "correct response": "the Impala", "Triple Stumper": true}, "(5, 3)": {"clue": "\"I taste a liquor never brewed-- / From tankards scooped in Pearl-- / Not all the vats on the Rhine / Yield such an alcohol\"", "clue_order_number": 3, "correct response": "(Emily) Dickinson", "correct": "Susan"}, "(6, 3)": {"clue": "Not a comment on originality, but for etymology: der.", "clue_order_number": 17, "correct response": "a derivative (derivation accepted)", "correct": "Sean"}, "(1, 4)": {"clue": "Article II section 2 allows the president to grant pardons except in cases of this, to which section 4 makes him liable", "clue_order_number": 12, "correct response": "impeachment", "wrong0": "Sean", "Daily Double": true}, "(2, 4)": {"clue": "In 1977 this Miami field general became the first NFL quarterback to wear glasses on the field", "clue_order_number": 29, "correct response": "Bob Griese", "Triple Stumper": true}, "(3, 4)": {"clue": "In Alabama there's one just north of Tuscumbia; in California, it's a neighbor of San Francisco", "clue_order_number": 15, "correct response": "Oakland", "correct": "Regina"}, "(4, 4)": {"clue": "Amtrak's Downeaster runs between Boston & this city, the largest in its state", "clue_order_number": 24, "correct response": "Portland", "Triple Stumper": true}, "(5, 4)": {"clue": "\"One short sleep past, we wake eternally, / And death shall be no more; Death, thou shalt die\"", "clue_order_number": 4, "correct response": "John Donne", "correct": "Sean"}, "(6, 4)": {"clue": "A grammatical case: nom.", "clue_order_number": 18, "correct response": "the nominative", "correct": "Susan"}, "(1, 5)": {"clue": "The constitution's last & shortest article, it spells out the ratification process", "clue_order_number": 20, "correct response": "the seventh", "correct": "Sean"}, "(3, 5)": {"clue": "Population 500, it hunts in a large constellation", "clue_order_number": 21, "correct response": "Orion", "correct": "Regina"}, "(4, 5)": {"clue": "In 2001 NASA's solar-powered plane named for this Greek sun god reached a record altitude of 96,863 feet", "clue_order_number": 25, "correct response": "Helios", "correct": "Regina", "wrong0": "Sean"}, "(5, 5)": {"clue": "\"Daddy, I have had to kill you. You died before I had time\"", "clue_order_number": 5, "correct response": "(Sylvia) Plath", "correct": "Regina"}, "(6, 5)": {"clue": "The mood of a verb: subj.", "clue_order_number": 19, "correct response": "subjunctive", "correct": "Sean"}}, "FJ": {"(0, 0)": {"clue": "You can reach this town's convention & visitors bureau by calling 1-TOMANDHUCK"}}}}