{"info": {"show number": 4955, "date": "2006-03-10", "game_id": 831, "game_comments": "", "scores": {"first_break": [2400, 2800, 1200], "J_round": [2800, 6800, 2800], "DJ_round": [8000, 6800, 15900], "final": [0, 13400, 15799], "coryat": [8000, 5600, 13200]}}, "categories": {"jeopardy_round": ["FAR OUT", "SUPER COOL", "23 SKIDOO", "GROOVY", "GOLLY \"G\"!", "LET'S SPLIT!"], "double_jeopardy_round": ["LITERATURE", "ALL THAT JAZZ", "-ISMS", "QUOTABLE WOMEN", "SOUTH CAROLINA", "TOM SWIFTIES"], "final_jeopardy_round": ["HISTORIC DOCUMENTS"]}, "contestants": {"1": {"player_name": "Randy Logan", "player_id": 1682}, "2": {"player_name": "Brett Crawford", "player_id": 1691}, "3": {"player_name": "Chris Smith", "player_id": 1690}}, "clues": {"J": {"(1, 1)": {"clue": "From Earth 4 galaxies are visible without a telescope: the Large & Small Magellanic Clouds, Andromeda & this", "clue_order_number": 6, "correct response": "the Milky Way", "correct": "Brett"}, "(2, 1)": {"clue": "The \"Rachel cut\" hairstyle was popularized by this sitcom", "clue_order_number": 11, "correct response": "Friends", "correct": "Chris"}, "(3, 1)": {"clue": "Early in the morning of August 3, 1923 he was sworn in as U.S. president", "clue_order_number": 15, "correct response": "(Calvin) Coolidge", "correct": "Randy", "wrong0": "Chris"}, "(4, 1)": {"clue": "In carpentry, this body part \"& groove\" form a joint between 2 boards", "clue_order_number": 21, "correct response": "tongue", "correct": "Chris"}, "(5, 1)": {"clue": "A home run with the bases loaded", "clue_order_number": 1, "correct response": "a grand slam", "correct": "Brett"}, "(6, 1)": {"clue": "In 2000 Judge Thomas Penfield Jackson ruled that this computer company should be split in two", "clue_order_number": 26, "correct response": "Microsoft", "correct": "Brett"}, "(1, 2)": {"clue": "The possible 10th planet of our solar system was nicknamed for this TV warrior princess; Gabrielle is its moon", "clue_order_number": 7, "correct response": "Xena", "correct": "Randy"}, "(2, 2)": {"clue": "Tourists flocked to California wineries after seeing this 2004 Paul Giamatti film but probably held off on the Merlot", "clue_order_number": 12, "correct response": "Sideways", "correct": "Randy"}, "(3, 2)": {"clue": "In 1923 this city replaced Constantinople as the capital of its country", "clue_order_number": 16, "correct response": "Ankara", "correct": "Brett"}, "(4, 2)": {"clue": "Seen here are grooves in this Buckeye State scoured into limestone 18,000 years ago by the Great Ice Sheet", "clue_order_number": 22, "correct response": "Ohio", "correct": "Randy"}, "(5, 2)": {"clue": "\"Colorful\" 9-letter word used derisively of an immigrant unfamiliar with American life", "clue_order_number": 2, "correct response": "a greenhorn", "correct": "Chris"}, "(6, 2)": {"clue": "Grammar alert: there's a split one of these in the phrase \"He chose to wisely decline the invitation\"", "clue_order_number": 27, "correct response": "an infinitive", "correct": "Chris"}, "(1, 3)": {"clue": "Appropriately, the star Acubens, \"The Claw\", is found in this constellation named for a crustacean", "clue_order_number": 8, "correct response": "the Crab Constellation (Cancer accepted)", "correct": "Randy", "wrong0": "Chris"}, "(2, 3)": {"clue": "In the '90s this somewhat hallucinatory TV title attorney brought back the micro-miniskirt", "clue_order_number": 13, "correct response": "Ally McBeal", "correct": "Brett"}, "(3, 3)": {"clue": "Alfred P. Sloan Jr. became the CEO of this giant auto company in 1923 & brought it back from the brink of collapse", "clue_order_number": 17, "correct response": "General Motors", "correct": "Brett"}, "(4, 3)": {"clue": "Much of the cortical surface of this is hidden in grooves called sulci", "clue_order_number": 23, "correct response": "the brain", "correct": "Chris"}, "(5, 3)": {"clue": "He's the first astronaut later elected U.S. senator", "clue_order_number": 3, "correct response": "John Glenn", "correct": "Chris"}, "(6, 3)": {"clue": "Otto Hahn & Fritz Strassman got together long enough to split this in 1938", "clue_order_number": 28, "correct response": "the atom", "correct": "Chris"}, "(1, 4)": {"clue": "Fomalhaut, the brightest star in Piscis Austrinus, means \"mouth of\" this in Arabic", "clue_order_number": 9, "correct response": "a fish", "correct": "Chris"}, "(2, 4)": {"clue": "In 2005 the terpsichorean splendor of John O'Hurley repopularized a somewhat lost art on this TV show", "clue_order_number": 14, "correct response": "Dancing with the Stars", "correct": "Randy"}, "(3, 4)": {"clue": "Governor Al Smith of this state signed a repeal of the state's Prohibition Enforcement Act, angering the feds", "clue_order_number": 18, "correct response": "New York", "correct": "Brett", "Daily Double": true}, "(4, 4)": {"clue": "This Simon & Garfunkel tune is also known as \"The 59th Street Bridge Song\"", "clue_order_number": 24, "correct response": "\"Feelin\\' Groovy\"", "correct": "Chris"}, "(5, 4)": {"clue": "January is the first month of the year on this, first used in 1582", "clue_order_number": 4, "correct response": "the Gregorian calendar", "correct": "Brett"}, "(6, 4)": {"clue": "Kenya, Tanzania & Uganda share ownership of this body of water", "clue_order_number": 29, "correct response": "Lake Victoria", "correct": "Brett"}, "(1, 5)": {"clue": "Named in the 17th c. by Dutchman Petrus Plancius, the constellation Monoceros represents this mythical animal", "clue_order_number": 10, "correct response": "a unicorn", "correct": "Brett", "wrong0": "Chris"}, "(2, 5)": {"clue": "Sales of Ray-Ban Wayfarer sunglasses soared after Tom Cruise donned a pair in this 1983 film", "clue_order_number": 20, "correct response": "Risky Business", "correct": "Randy"}, "(3, 5)": {"clue": "In July the U.S. Open golf tournament was won by this amateur in a playoff", "clue_order_number": 19, "correct response": "Bobby Jones", "wrong0": "Chris", "Triple Stumper": true}, "(4, 5)": {"clue": "In this artistic process, printing is done by forcing ink into grooves made by acid", "clue_order_number": 25, "correct response": "copperplate etching", "wrong0": "Randy", "wrong1": "Chris", "Triple Stumper": true}, "(5, 5)": {"clue": "Psychologist Max Wertheimer co-founded this theory in which the sum is greater than its parts", "clue_order_number": 5, "correct response": "Gestalt", "correct": "Chris"}, "(6, 5)": {"clue": "Name given to the period between 1378 & 1417 when the Catholic Church had 2 or 3 popes serving simultaneously", "clue_order_number": 30, "correct response": "the Great Schism", "correct": "Chris"}}, "DJ": {"(1, 1)": {"clue": "Britannica states that the name \"Agora\" was first found in the work of this ancient Greek poet", "clue_order_number": 1, "correct response": "Homer", "correct": "Brett"}, "(2, 1)": {"clue": "\"Miles Ahead\" is a 1957 album by this jazz trumpeter", "clue_order_number": 6, "correct response": "Miles Davis", "correct": "Brett"}, "(3, 1)": {"clue": "Eponymous term meaning biased devotion to a group, it sometimes follows \"male\" when used by feminists", "clue_order_number": 12, "correct response": "chauvinism", "correct": "Chris"}, "(4, 1)": {"clue": "Freed from prison in 2005, she said, \"The experience of the last five months... has been life altering and life affirming\"", "clue_order_number": 23, "correct response": "Martha Stewart", "correct": "Brett"}, "(5, 1)": {"clue": "S.C. native Robert Mills designed the Washington Monument & some of the USC campus in this state capital", "clue_order_number": 21, "correct response": "Columbia", "correct": "Brett"}, "(6, 1)": {"clue": "\"The herb you need to improve this recipe isn't parsley, rosemary or thyme\", Tom remarked in this wise fashion", "clue_order_number": 11, "correct response": "sagely", "correct": "Brett"}, "(1, 2)": {"clue": "This 1953 book title tells us the temperature at which books burn", "clue_order_number": 2, "correct response": "Fahrenheit 451", "correct": "Brett"}, "(2, 2)": {"clue": "(Cheryl of the Clue Crew reports from the Smithsonian Institution.)  This Grammy is one of 13 awarded to this jazz singer called \"The First Lady of Song\"", "clue_order_number": 7, "correct response": "Ella Fitzgerald", "wrong0": "Chris", "Triple Stumper": true}, "(3, 2)": {"clue": "Part of many religions, it's the opposition to war & violence as means of settling disputes", "clue_order_number": 13, "correct response": "pacifism", "correct": "Chris"}, "(4, 2)": {"clue": "Dorothy Parker quipped that \"Brevity is the soul of\" this sexywear", "clue_order_number": 24, "correct response": "lingerie", "correct": "Chris"}, "(5, 2)": {"clue": "The Francis Marion National Forest contains plenty of these soggy areas found in Marion's nickname", "clue_order_number": 22, "correct response": "swamps", "correct": "Randy", "wrong0": "Chris"}, "(6, 2)": {"clue": "\"I've struck unrefined oil!\" Tom related in this coarse manner", "clue_order_number": 17, "correct response": "crudely", "correct": "Chris"}, "(1, 3)": {"clue": "In 1900 he wrote the line, \"The road to the City of Emeralds is paved with yellow brick\"", "clue_order_number": 3, "correct response": "L. Frank Baum", "correct": "Randy"}, "(2, 3)": {"clue": "The album title \"Satch Plays Fats\" refers to these 2 musicians, one a trumpeter, the other a pianist", "clue_order_number": 8, "correct response": "Louis Armstrong & Fats Waller", "correct": "Chris"}, "(3, 3)": {"clue": "The practices of some extreme Protestants of the Reformation era; or any moral strictness", "clue_order_number": 14, "correct response": "puritanism", "correct": "Chris", "Daily Double": true}, "(4, 3)": {"clue": "She once remarked, \"The power I exert on the court depends on the power of my arguments, not on my gender\"", "clue_order_number": 25, "correct response": "Sandra Day O\\'Connor", "wrong0": "Brett", "Triple Stumper": true}, "(5, 3)": {"clue": "2 crops, indigo & this grain, made the colony wealthy in the 18th century", "clue_order_number": 28, "correct response": "rice", "correct": "Chris"}, "(6, 3)": {"clue": "\"I only have clubs, diamonds and spades\", Tom said in this cruel fashion", "clue_order_number": 18, "correct response": "heartlessly", "Triple Stumper": true}, "(1, 4)": {"clue": "This 1952 Pulitzer-winning book grew out of Herman Wouk's experiences on a WWII destroyer-minesweeper", "clue_order_number": 4, "correct response": "The Caine Mutiny", "correct": "Randy", "wrong0": "Brett", "wrong1": "Chris"}, "(2, 4)": {"clue": "This bop saxophonist's 1946 tune \"Ornithology\" became a jazz standard", "clue_order_number": 9, "correct response": "Charlie Parker", "correct": "Chris", "Daily Double": true}, "(3, 4)": {"clue": "Latin for \"other\" gave us this word meaning unselfish concern for others", "clue_order_number": 15, "correct response": "altruism", "Triple Stumper": true}, "(4, 4)": {"clue": "In 1926 she told Ernest Hemingway, \"You are all a lost generation\"", "clue_order_number": 26, "correct response": "Gertrude Stein", "correct": "Randy"}, "(6, 4)": {"clue": "It's the annoyingly cheerful way Tom said, \"Golly!  The coffee's bubbling through!\"", "clue_order_number": 19, "correct response": "perkily", "correct": "Chris"}, "(1, 5)": {"clue": "Elizabeth Barrett Browning gave this volume of 44 sonnets to Robert in 1847, a year after they eloped", "clue_order_number": 5, "correct response": "Sonnets from the Portuguese", "wrong0": "Randy", "Triple Stumper": true}, "(2, 5)": {"clue": "This bandleader was the \"King of Hi-De-Ho\"", "clue_order_number": 10, "correct response": "Cab Calloway", "correct": "Randy"}, "(3, 5)": {"clue": "(Kelly of the Clue Crew explains a symbol pictured on a screen.)  A Roman symbol in which rods tied together meant unity led to the name of this ideology that glorifies the state", "clue_order_number": 16, "correct response": "fascism", "correct": "Chris"}, "(4, 5)": {"clue": "\"People said women couldn't swim the Channel... I proved they could\"; & so she did, in 1926", "clue_order_number": 27, "correct response": "Gertrude Ederle", "Triple Stumper": true}, "(6, 5)": {"clue": "When Tom yelled, \"Neigh!  Neigh!  A thousand times neigh!\" it was in this rough way, as if he had a sore throat", "clue_order_number": 20, "correct response": "hoarsely", "correct": "Chris"}}, "FJ": {"(0, 0)": {"clue": "Clause 39 of this reads \"No freeman shall be taken, or imprisoned... except by the legal judgment of his peers\""}}}}